odoo/addons/repair_calendar_view/README.rst
odoo/addons/repair_calendar_view/__init__.py
odoo/addons/repair_calendar_view/__manifest__.py
odoo/addons/repair_calendar_view/i18n/ar.po
odoo/addons/repair_calendar_view/i18n/bs.po
odoo/addons/repair_calendar_view/i18n/ca.po
odoo/addons/repair_calendar_view/i18n/cs.po
odoo/addons/repair_calendar_view/i18n/de.po
odoo/addons/repair_calendar_view/i18n/en_GB.po
odoo/addons/repair_calendar_view/i18n/es.po
odoo/addons/repair_calendar_view/i18n/es_CR.po
odoo/addons/repair_calendar_view/i18n/es_EC.po
odoo/addons/repair_calendar_view/i18n/es_MX.po
odoo/addons/repair_calendar_view/i18n/es_VE.po
odoo/addons/repair_calendar_view/i18n/et.po
odoo/addons/repair_calendar_view/i18n/fi.po
odoo/addons/repair_calendar_view/i18n/fr.po
odoo/addons/repair_calendar_view/i18n/gl.po
odoo/addons/repair_calendar_view/i18n/hr.po
odoo/addons/repair_calendar_view/i18n/hr_HR.po
odoo/addons/repair_calendar_view/i18n/hu.po
odoo/addons/repair_calendar_view/i18n/id.po
odoo/addons/repair_calendar_view/i18n/it.po
odoo/addons/repair_calendar_view/i18n/ja.po
odoo/addons/repair_calendar_view/i18n/lt.po
odoo/addons/repair_calendar_view/i18n/lv.po
odoo/addons/repair_calendar_view/i18n/mk.po
odoo/addons/repair_calendar_view/i18n/mn.po
odoo/addons/repair_calendar_view/i18n/mrp_repair_calendar_view.pot
odoo/addons/repair_calendar_view/i18n/nb.po
odoo/addons/repair_calendar_view/i18n/nl.po
odoo/addons/repair_calendar_view/i18n/nl_BE.po
odoo/addons/repair_calendar_view/i18n/nl_NL.po
odoo/addons/repair_calendar_view/i18n/pl.po
odoo/addons/repair_calendar_view/i18n/pt.po
odoo/addons/repair_calendar_view/i18n/pt_BR.po
odoo/addons/repair_calendar_view/i18n/pt_PT.po
odoo/addons/repair_calendar_view/i18n/repair_calendar_view.pot
odoo/addons/repair_calendar_view/i18n/ro.po
odoo/addons/repair_calendar_view/i18n/ru.po
odoo/addons/repair_calendar_view/i18n/sl.po
odoo/addons/repair_calendar_view/i18n/sr@latin.po
odoo/addons/repair_calendar_view/i18n/sv.po
odoo13_addon_repair_calendar_view-13.0.1.0.1.dev4.dist-info/METADATA
odoo13_addon_repair_calendar_view-13.0.1.0.1.dev4.dist-info/WHEEL
odoo13_addon_repair_calendar_view-13.0.1.0.1.dev4.dist-info/top_level.txt
odoo13_addon_repair_calendar_view-13.0.1.0.1.dev4.dist-info/RECORD
